francisco_diaz/__init__.py
francisco_diaz/__main__.py
francisco_diaz/names.txt
francisco_diaz/speaker.py
francisco_diaz/speakers/__init__.py
francisco_diaz/speakers/francisco.py
francisco_diaz-0.0.5.dist-info/licenses/LICENSE.txt
francisco_diaz-0.0.5.dist-info/METADATA
francisco_diaz-0.0.5.dist-info/WHEEL
francisco_diaz-0.0.5.dist-info/entry_points.txt
francisco_diaz-0.0.5.dist-info/top_level.txt
francisco_diaz-0.0.5.dist-info/RECORD
