Metadata-Version: 2.4
Name: francisco_diaz
Version: 0.0.5
Summary: simple python package for testing
Author-email: Francisco Diaz <fxcisco.contact@gmail.com>
Maintainer-email: Francisco Diaz <fxcisco.contact@gmail.com>
License-Expression: BSD-3-Clause
Project-URL: Homepage, https://github.com/fxcisco/francisco_diaz
Project-URL: Documentation, https://github.com/fxcisco/francisco_diaz/README.md
Keywords: francisco
Classifier: Programming Language :: Python :: 3
Classifier: Intended Audience :: Developers
Classifier: Operating System :: POSIX :: Linux
Classifier: Operating System :: MacOS :: MacOS X
Classifier: Operating System :: Microsoft :: Windows
Requires-Python: >=3.10
License-File: LICENSE.txt
Requires-Dist: colorama~=0.0
Provides-Extra: dev
Requires-Dist: twine; extra == "dev"
Requires-Dist: build; extra == "dev"
Dynamic: license-file
